k8s_install_mcp/__init__.py
k8s_install_mcp/server.py
k8s_install_mcp/core/__init__.py
k8s_install_mcp/core/commands.py
k8s_install_mcp/core/ssh_client.py
k8s_install_mcp/function/__init__.py
k8s_install_mcp/function/install.py
k8s_install_mcp/function/utils.py
k8s_install_mcp-0.1.3.dist-info/METADATA
k8s_install_mcp-0.1.3.dist-info/WHEEL
k8s_install_mcp-0.1.3.dist-info/entry_points.txt
k8s_install_mcp-0.1.3.dist-info/RECORD
