Metadata-Version: 2.4
Name: k8s-install-mcp
Version: 0.1.3
Summary: mcp k8s auto install
Author-email: maruduke <abab1117@naver.com>
Requires-Python: >=3.12
Requires-Dist: mcp[cli]>=1.9.2
Requires-Dist: paramiko>=3.5.1
Requires-Dist: setuptools>=80.9.0
